oyente/__init__.py
oyente/analysis.py
oyente/ast_helper.py
oyente/ast_walker.py
oyente/basicblock.py
oyente/batch_run.py
oyente/ethereum_data.py
oyente/ethereum_data1.py
oyente/global_params.py
oyente/opcodes.py
oyente/oyente.py
oyente/run_tests.py
oyente/source_map.py
oyente/state.json
oyente/symExec.py
oyente/utils.py
oyente/validator.py
oyente/vargenerator.py
oyente/test_evm/__init__.py
oyente/test_evm/evm_unit_test.py
oyente/test_evm/global_test_params.py
oyente-0.2.7.dist-info/DESCRIPTION.rst
oyente-0.2.7.dist-info/METADATA
oyente-0.2.7.dist-info/RECORD
oyente-0.2.7.dist-info/WHEEL
oyente-0.2.7.dist-info/entry_points.txt
oyente-0.2.7.dist-info/metadata.json
oyente-0.2.7.dist-info/top_level.txt
