Metadata-Version: 2.0
Name: oyente
Version: 0.2.7
Summary: An analysis tool for smart contracts
Home-page: https://github.com/melonport/oyente
Author: Loi Luu
Author-email: UNKNOWN
License: GPL
Keywords: ethereum smart contracts
Platform: UNKNOWN
Classifier: Environment :: Console
Classifier: Development Status :: 4 - Beta
Classifier: Intended Audience :: Developers
Classifier: Intended Audience :: End Users/Desktop
Classifier: Intended Audience :: Information Technology
Classifier: Intended Audience :: System Administrators
Classifier: License :: OSI Approved :: BSD License
Classifier: Operating System :: POSIX
Classifier: Operating System :: MacOS :: MacOS X
Classifier: Programming Language :: Python
Classifier: Topic :: Utilities
Requires-Dist: requests
Requires-Dist: web3
Requires-Dist: z3-solver
